bw_interface_schemas/__init__.py
bw_interface_schemas/graph.py
bw_interface_schemas/models.py
bw_interface_schemas/json_schema/biosphere_quantitative_edge.json
bw_interface_schemas/json_schema/characterization_quantitative_edge.json
bw_interface_schemas/json_schema/data_source.json
bw_interface_schemas/json_schema/database.json
bw_interface_schemas/json_schema/edge.json
bw_interface_schemas/json_schema/elementary_flow.json
bw_interface_schemas/json_schema/impact_assessment_method.json
bw_interface_schemas/json_schema/impact_category.json
bw_interface_schemas/json_schema/inventory_node.json
bw_interface_schemas/json_schema/node.json
bw_interface_schemas/json_schema/normalization.json
bw_interface_schemas/json_schema/normalization_quantitative_edge.json
bw_interface_schemas/json_schema/process.json
bw_interface_schemas/json_schema/product.json
bw_interface_schemas/json_schema/project.json
bw_interface_schemas/json_schema/qualitative_edge.json
bw_interface_schemas/json_schema/quantitative_edge.json
bw_interface_schemas/json_schema/technosphere_quantitative_edge.json
bw_interface_schemas/json_schema/weighting.json
bw_interface_schemas/json_schema/weighting_quantitative_edge.json
bw_interface_schemas-0.2.dist-info/LICENSE
bw_interface_schemas-0.2.dist-info/METADATA
bw_interface_schemas-0.2.dist-info/WHEEL
bw_interface_schemas-0.2.dist-info/top_level.txt
bw_interface_schemas-0.2.dist-info/RECORD
